neuroscangen/__init__.py
neuroscangen/foo.py
neuroscangen-0.0.2.dist-info/LICENSE
neuroscangen-0.0.2.dist-info/METADATA
neuroscangen-0.0.2.dist-info/WHEEL
neuroscangen-0.0.2.dist-info/top_level.txt
neuroscangen-0.0.2.dist-info/RECORD
