Metadata-Version: 2.2
Name: neuroscangen
Version: 0.0.2
Summary: Generative AI with brain CT-scans.
Author-email: Thomas Boulier <tboulier@chu-grenoble.fr>
License: MIT
Project-URL: Repository, https://github.com/tomboulier/neuroscangen
Keywords: generative ai,ai,genai,gen ai,ct-scan,brain,neuroscience
Classifier: Programming Language :: Python
Classifier: Programming Language :: Python :: 3
Classifier: Topic :: Scientific/Engineering
Classifier: Topic :: Scientific/Engineering :: Artificial Intelligence
Classifier: Topic :: Scientific/Engineering :: Bio-Informatics
Classifier: Topic :: Scientific/Engineering :: Medical Science Apps.
Classifier: License :: OSI Approved :: MIT License
Classifier: Development Status :: 2 - Pre-Alpha
Requires-Python: <4.0,>=3.9
License-File: LICENSE
